{"nodes": [{"id": "games_codecritter_battle_status_lua", "label": "status.lua", "file_type": "code", "source_file": "games/codecritter/battle/status.lua", "source_location": "L1"}, {"id": "status_m_apply", "label": "M.apply()", "file_type": "code", "source_file": "games/codecritter/battle/status.lua", "source_location": "L71"}, {"id": "status_m_apply_turn_start", "label": "M.apply_turn_start()", "file_type": "code", "source_file": "games/codecritter/battle/status.lua", "source_location": "L85"}, {"id": "status_m_tick", "label": "M.tick()", "file_type": "code", "source_file": "games/codecritter/battle/status.lua", "source_location": "L92"}, {"id": "status_m_clear", "label": "M.clear()", "file_type": "code", "source_file": "games/codecritter/battle/status.lua", "source_location": "L108"}, {"id": "status_m_describe", "label": "M.describe()", "file_type": "code", "source_file": "games/codecritter/battle/status.lua", "source_location": "L117"}], "edges": [{"source": "games_codecritter_battle_status_lua", "target": "status_m_apply", "relation": "contains", "confidence": "EXTRACTED", "source_file": "games/codecritter/battle/status.lua", "source_location": "L71", "weight": 1.0}, {"source": "games_codecritter_battle_status_lua", "target": "status_m_apply_turn_start", "relation": "contains", "confidence": "EXTRACTED", "source_file": "games/codecritter/battle/status.lua", "source_location": "L85", "weight": 1.0}, {"source": "games_codecritter_battle_status_lua", "target": "status_m_tick", "relation": "contains", "confidence": "EXTRACTED", "source_file": "games/codecritter/battle/status.lua", "source_location": "L92", "weight": 1.0}, {"source": "games_codecritter_battle_status_lua", "target": "status_m_clear", "relation": "contains", "confidence": "EXTRACTED", "source_file": "games/codecritter/battle/status.lua", "source_location": "L108", "weight": 1.0}, {"source": "games_codecritter_battle_status_lua", "target": "status_m_describe", "relation": "contains", "confidence": "EXTRACTED", "source_file": "games/codecritter/battle/status.lua", "source_location": "L117", "weight": 1.0}]}